LICENSE
MANIFEST.in
README.md
setup.py
netas_olap_dbapi/__init__.py
netas_olap_dbapi/__version__.py
netas_olap_dbapi/console.py
netas_olap_dbapi/db.py
netas_olap_dbapi/exceptions.py
netas_olap_dbapi/ssas_sqlalchemy.py
netas_olap_dbapi.egg-info/PKG-INFO
netas_olap_dbapi.egg-info/SOURCES.txt
netas_olap_dbapi.egg-info/dependency_links.txt
netas_olap_dbapi.egg-info/entry_points.txt
netas_olap_dbapi.egg-info/requires.txt
netas_olap_dbapi.egg-info/top_level.txt