Metadata-Version: 2.1
Name: netas-olap-dbapi
Version: 0.1.12.1
Summary: Python DB-API and SQLAlchemy interface for OLAP.
Home-page: https://github.com/mfyuce/netas-olap-dbapi
Author: Beto Dealmeida + Mehmet F. YUCE
Author-email: mfyuce@netas.com.tr
License: MIT
Platform: UNKNOWN
Classifier: License :: OSI Approved :: MIT License
Classifier: Programming Language :: Python
Classifier: Programming Language :: Python :: 2.6
Classifier: Programming Language :: Python :: 2.7
Classifier: Programming Language :: Python :: 3
Classifier: Programming Language :: Python :: 3.3
Classifier: Programming Language :: Python :: 3.4
Classifier: Programming Language :: Python :: 3.5
Classifier: Programming Language :: Python :: 3.6
Classifier: Programming Language :: Python :: Implementation :: CPython
Classifier: Programming Language :: Python :: Implementation :: PyPy
Provides-Extra: sqlalchemy
Provides-Extra: cli
Provides-Extra: dev
